[
  {
    "fullName": "Mitchell Trubisky",
    "givenNames": [
      "Mitchell",
      "David"
    ],
    "familyName": "Trubisky",
    "wikipedia": "https://en.wikipedia.org/wiki/Mitchell_Trubisky",
    "occupation": "American Football Player",
    "achievements": [
      "Quarterback for the Pittsburgh Steelers.",
      "Selected second overall in the 2017 NFL Draft."
    ],
    "yearBorn": 1994
  },
  {
    "fullName": "Mitchell Schwartz",
    "givenNames": [
      "Mitchell",
      "Bryan"
    ],
    "familyName": "Schwartz",
    "wikipedia": "https://en.wikipedia.org/wiki/Mitchell_Schwartz",
    "occupation": "American Football Player",
    "achievements": [
      "Offensive tackle who played for the Cleveland Browns and Kansas City Chiefs.",
      "Super Bowl LIV champion with the Chiefs."
    ],
    "yearBorn": 1989
  },
  {
    "fullName": "Mitchell Santner",
    "givenNames": [
      "Mitchell",
      "Josef"
    ],
    "familyName": "Santner",
    "wikipedia": "https://en.wikipedia.org/wiki/Mitchell_Santner",
    "occupation": "Cricketer",
    "achievements": [
      "New Zealand international cricketer",
      "Known for his left-arm spin bowling and aggressive batting"
    ],
    "yearBorn": 1992
  }
]