[
  {
    "fullName": "Serge Gainsbourg",
    "givenNames": [
      "Serge"
    ],
    "familyName": "Gainsbourg",
    "wikipedia": "https://en.wikipedia.org/wiki/Serge_Gainsbourg",
    "occupation": "Singer-songwriter, actor, painter, director, and poet",
    "achievements": [
      "Prolific and influential figure in French popular music",
      "Known for his provocative lyrics and eclectic musical style",
      "Recipient of multiple awards, including the César Award for Best Original Music Score"
    ],
    "yearBorn": 1928,
    "yearDied": 1991
  }
]