[
  {
    "fullName": "Hideko Takamine",
    "givenNames": [
      "Hideko"
    ],
    "familyName": "Takamine",
    "wikipedia": "https://en.wikipedia.org/wiki/Hideko_Takamine",
    "occupation": "Actress",
    "achievements": [
      "Prolific actress in Japanese cinema during the Golden Age",
      "Known for her roles in films directed by Akira Kurosawa and Kenji Mizoguchi",
      "Recipient of numerous awards, including the Japan Academy Prize for Lifetime Achievement"
    ],
    "yearBorn": 1924,
    "yearDied": 2010
  }
]