[
  {
    "fullName": "Kimberly Guilfoyle",
    "givenNames": [
      "Kimberly",
      "Ann"
    ],
    "familyName": "Guilfoyle",
    "wikipedia": "https://en.wikipedia.org/wiki/Kimberly_Guilfoyle",
    "occupation": "Television personality, attorney",
    "achievements": [
      "Former prosecutor for San Francisco and Los Angeles.",
      "Co-host of 'The Five' on Fox News."
    ],
    "yearBorn": 1969
  },
  {
    "fullName": "Kimberly Peirce",
    "givenNames": [
      "Kimberly",
      "Ane"
    ],
    "familyName": "Peirce",
    "wikipedia": "https://en.wikipedia.org/wiki/Kimberly_Peirce",
    "occupation": "Film director, screenwriter",
    "achievements": [
      "Directed the films 'Boys Don't Cry' and 'Stop-Loss'."
    ],
    "yearBorn": 1967
  },
  {
    "fullName": "Kimberly Elise",
    "givenNames": [
      "Kimberly"
    ],
    "familyName": "Elise",
    "wikipedia": "https://en.wikipedia.org/wiki/Kimberly_Elise",
    "occupation": "Actress",
    "achievements": [
      "NAACP Image Award for Outstanding Actress in a Motion Picture"
    ],
    "yearBorn": 1967
  }
]